<?xml version="1.0" encoding="UTF-8" ?>
<!DOCTYPE mapper PUBLIC "-//mybatis.org//DTD Mapper 3.0//EN" "http://mybatis.org/dtd/mybatis-3-mapper.dtd" >
<mapper namespace="com.yuantu.dao.tcsalesman.MeslReceiveMapper">
    <resultMap id="BaseResultMap" type="com.yuantu.entity.tcsalesman.MeslReceive">
        <!--
          WARNING - @mbggenerated
          This element is automatically generated by MyBatis Generator, do not modify.
          This element was generated on Fri Jun 28 14:34:58 CST 2019.
        -->
        <result column="id" property="id" jdbcType="INTEGER"/>
        <result column="receive_number" property="receiveNumber" jdbcType="VARCHAR"/>
        <result column="receive_time" property="receiveTime" jdbcType="VARCHAR"/>
        <result column="origin" property="origin" jdbcType="VARCHAR"/>
        <result column="receive_place" property="receivePlace" jdbcType="VARCHAR"/>
        <result column="freight_batch_number" property="freightBatchNumber" jdbcType="VARCHAR"/>
        <result column="freight" property="freight" jdbcType="VARCHAR"/>
    </resultMap>
    <insert id="insert" parameterType="com.yuantu.entity.tcsalesman.MeslReceive">
        <!--
          WARNING - @mbggenerated
          This element is automatically generated by MyBatis Generator, do not modify.
          This element was generated on Fri Jun 28 14:34:58 CST 2019.
        -->
        <selectKey resultType="java.lang.Integer" keyProperty="id" order="AFTER">
            SELECT LAST_INSERT_ID()
        </selectKey>
        insert into mesl_receive (receive_number, receive_time, origin,
        receive_place, freight_batch_number, freight
        )
        values (#{receiveNumber,jdbcType=VARCHAR}, #{receiveTime,jdbcType=VARCHAR}, #{origin,jdbcType=VARCHAR},
        #{receivePlace,jdbcType=VARCHAR}, #{freightBatchNumber,jdbcType=VARCHAR}, #{freight,jdbcType=VARCHAR}
        )
    </insert>
    <insert id="insertSelective" parameterType="com.yuantu.entity.tcsalesman.MeslReceive">
        <!--
          WARNING - @mbggenerated
          This element is automatically generated by MyBatis Generator, do not modify.
          This element was generated on Fri Jun 28 14:34:58 CST 2019.
        -->
        <selectKey resultType="java.lang.Integer" keyProperty="id" order="AFTER">
            SELECT LAST_INSERT_ID()
        </selectKey>
        insert into mesl_receive
        <trim prefix="(" suffix=")" suffixOverrides=",">
            <if test="receiveNumber != null">
                receive_number,
            </if>
            <if test="receiveTime != null">
                receive_time,
            </if>
            <if test="origin != null">
                origin,
            </if>
            <if test="receivePlace != null">
                receive_place,
            </if>
            <if test="freightBatchNumber != null">
                freight_batch_number,
            </if>
            <if test="freight != null">
                freight,
            </if>
        </trim>
        <trim prefix="values (" suffix=")" suffixOverrides=",">
            <if test="receiveNumber != null">
                #{receiveNumber,jdbcType=VARCHAR},
            </if>
            <if test="receiveTime != null">
                #{receiveTime,jdbcType=VARCHAR},
            </if>
            <if test="origin != null">
                #{origin,jdbcType=VARCHAR},
            </if>
            <if test="receivePlace != null">
                #{receivePlace,jdbcType=VARCHAR},
            </if>
            <if test="freightBatchNumber != null">
                #{freightBatchNumber,jdbcType=VARCHAR},
            </if>
            <if test="freight != null">
                #{freight,jdbcType=VARCHAR},
            </if>
        </trim>
    </insert>
    <insert id="insertReceive">
        insert into mesl_receive (receive_number, receive_time, origin, receive_place, freight_batch_number, freight)
        values (#{receiveNumber}, #{receiveTime}, #{origin}, #{receivePlace}, #{freightBatchNumber}, #{freight})
    </insert>
</mapper>